<?xml version='1.0' encoding='GB18030'?>
<Subs TM='1382773945'>
<Sub bigtvg="/95_3139_141832.html" 
				id="3139" 
				name="桌球基地" ord="letter" seq="desc" defaultopen="" playbreak="" op="sc='201';on='982';vm='8.3'" TM="1382090887" BKID="202625860" search="类型:联赛,杯赛,纪录片;产地:中国大陆,英国,德国;年份:2010;首字母:数字;时长:30分钟以内,30分钟-60分钟,60分钟-90分钟,90分钟-120分钟,120分钟以上;"
				 TP="g" col="0" pluson="6371" letter="Z"  tags="国语DVD版,国语TV版,外语流畅DVD版" isSeries="1" enableSearch2="1" image="2008-11/202625860-321-2008-11-11 09-29-58.jpg" fotm="2" />
<Sub 
				id="47367" 
				name="性感体坛" ord="time" seq="desc" defaultopen="" playbreak="" op="sc='197';on='977';vm='8.7'" TM="1382697137" BKID="202571792" search="类型:联赛;产地:中国大陆,美国;年份:2010,2008;首字母:A,B,C,D,E,G,H,J,K,L,M,N,P,Q,S,T,W,X,Y,Z,数字;时长:30分钟以内,30分钟-60分钟,60分钟-90分钟,90分钟-120分钟,120分钟以上;"
				 TP="g" col="0" pluson="6474" letter="X"  tags="国语DVD版,国语TV版,外语DVD版,外语TV版" isSeries="1" enableSearch2="1" image="2012-08/202571792-321-2012-08-13-14-58-34.jpg" fotm="2" />
<Sub bigtvg="/95_12071_141865.html" 
				id="12071" 
				name="武术散打" ord="letter" seq="desc" defaultopen="" playbreak="" op="sc='95';on='1842';vm='7.1'" TM="1382325604" BKID="202568821" search="类型:杯赛;产地:中国大陆;年份:2004;首字母:数字;时长:30分钟-60分钟,60分钟-90分钟,90分钟-120分钟,120分钟以上;"
				 TP="g" col="0" pluson="5622" letter="W"  tags="DVD版,TV版,高清DVD版,高清TV版" isSeries="1" enableSearch2="1" image="2010-01/202568821-321-2010-01-15 18-15-06.jpg" fotm="3" />
<Sub bigtvg="/95_435_141819.html" 
				id="435" 
				name="WWE-PPV大赛" ord="letter" seq="desc" defaultopen="" playbreak="" op="sc='40';on='606';vm='8.7'" TM="1381219087" BKID="400126076" search="类型:联赛;产地:美国;年份:2002;首字母:数字;时长:30分钟以内,30分钟-60分钟,60分钟-90分钟,90分钟-120分钟;"
				 TP="g" col="0" pluson="6893" letter="W"  tags="DVD版,TV版,高清DVD版" isSeries="1" enableSearch2="1" image="2012-03/400126076-954-2012-03-14-16-45-42.jpg" fotm="3" />
<Sub bigtvg="/95_8322_141857.html" 
				id="8322" 
				name="网球地带" ord="letter" seq="desc" defaultopen="" playbreak="" op="sc='400';on='2152';vm='8.7'" TM="1382697137" BKID="202581241" search="类型:杯赛;产地:中国大陆,美国,法国;首字母:L,W,数字;时长:30分钟以内,30分钟-60分钟,60分钟-90分钟,90分钟-120分钟,120分钟以上;"
				 TP="g" col="0" pluson="5206" letter="W"  tags="国语DVD版,国语TV版,外语DVD版,外语TV版" isSeries="1" enableSearch2="1" image="2012-06/202581241-954-2012-06-25-11-57-56.jpg" fotm="2" />
<Sub bigtvg="/95_3138_141825.html" 
				id="3138" 
				name="拳王争霸" ord="letter" seq="desc" defaultopen="" playbreak="" op="sc='164';on='1120';vm='6.5'" TM="1382410033" BKID="202644643" search="类型:杯赛;产地:中国大陆;首字母:数字;时长:30分钟以内,30分钟-60分钟,60分钟-90分钟,90分钟-120分钟,120分钟以上;"
				 TP="g" col="0" pluson="6348" letter="Q"  tags="国语DVD版,国语TV版,国语高清DVD版,外语DVD版,外语TV版" isSeries="1" enableSearch2="1" image="2009-04/202644643-321-2009-04-24 11-53-39.jpg" fotm="3" />
<Sub bigtvg="/95_37546_185567.html" 
				id="37546" 
				name="两代天王科比VS詹姆斯" ord="letter" seq="desc" defaultopen="" playbreak="" op="sc='50';on='276';vm='7.8'" TM="1382697943" BKID="202624195" search="类型:联赛,纪录片;产地:美国;首字母:N,数字;时长:30分钟以内;"
				 TP="g" col="0" pluson="7240" letter="L"  tags="国语DVD版,国语TV版,外语DVD版,外语TV版" isSeries="1" enableSearch2="1" image="2008-10/202624195-321-2008-10-10 09-53-42.jpg" fotm="2" />
<Sub bigtvg="/95_8846.html" 
				id="8846" 
				name="NBA劲爆篮球" ord="letter" seq="desc" defaultopen="" playbreak="" op="sc='394';on='2206';vm='7.8';nosa='uqPN4jvP47jbO8yozeU7sMTDxTvDwLn6Ow==';nofaop='uqPN4jvP47jbO8yozeU7sMTDxTvDwLn6Ow=='" TM="1382697943" BKID="202624195" search="类型:联赛,纪录片;产地:中国大陆,美国;年份:2010;首字母:N,数字;时长:30分钟以内,30分钟-60分钟,60分钟-90分钟;"
				 TP="g" col="0" pluson="5314" letter="N"  tags="国语DVD版,国语TV版,外语DVD版,外语TV版" isSeries="1" enableSearch2="1" image="2008-10/202624195-321-2008-10-10 09-53-42.jpg" fotm="2" dj="1" />
<Sub 
				id="47366" 
				name="综合体育" ord="letter" seq="desc" defaultopen="" playbreak="" op="sc='484';on='2545';vm='7.7'" TM="1382671221" BKID="202624375" search="类型:联赛;产地:中国大陆,美国;年份:2010;首字母:Z,数字;时长:30分钟以内,30分钟-60分钟;"
				 TP="g" col="0" pluson="4804" letter="Z"  tags="国语DVD版,国语TV版,外语DVD版,外语TV版" isSeries="1" enableSearch2="1" image="2013-10/202624375-321-2013-10-12-18-04-30.jpg" fotm="2" />
<Sub bigtvg="/95_26766_141511.html" 
				id="26766" 
				name="国际足球" ord="letter" seq="desc" defaultopen="" playbreak="" op="sc='820';on='4382';vm='8.5'" TM="1382697943" BKID="203216083" search="类型:联赛,杯赛;产地:英国;首字母:O,Z,数字;时长:30分钟以内,30分钟-60分钟,120分钟以上;"
				 TP="g" col="0" pluson="3001" letter="G"  tags="国语DVD版,国语TV版,国语流畅TV版,外语TV版" isSeries="1" enableSearch2="1" image="2012-11/203216083-954-2012-11-20-15-26-42.jpg" fotm="2" />
<Sub bigtvg="/95_17852_156692.html" 
				id="17852" 
				name="WWE世界摔跤RAW" ord="letter" seq="desc" defaultopen="" playbreak="" op="sc='86';on='3125';vm='8.6'" TM="1382583567" BKID="202801237" search="产地:美国;首字母:数字;时长:30分钟-60分钟,60分钟-90分钟,120分钟以上;"
				 TP="g" col="0" pluson="4390" letter="W"  tags="国语DVD版,国语TV版,国语高清DVD版,外语DVD版,外语TV版,外语高清DVD版" isSeries="1" enableSearch2="1" image="2011-06/202801237-954-2011-06-13-13-41-52.jpg" fotm="3" />
<Sub bigtvg="/95_17854_156677.html" 
				id="17854" 
				name="WWE世界摔跤NXT" ord="letter" seq="desc" defaultopen="" playbreak="" op="sc='39';on='257';vm='7.4'" TM="1382671984" BKID="202801235" search="产地:美国;首字母:数字;时长:30分钟-60分钟;"
				 TP="g" col="0" pluson="7220" letter="W"  tags="国语TV版,外语DVD版,外语TV版" isSeries="1" enableSearch2="1" image="2011-06/202801235-954-2011-06-13-13-26-52.jpg" fotm="2" />
<Sub bigtvg="/95_437_141827.html" 
				id="437" 
				name="TNA美国职业摔跤" ord="letter" seq="desc" defaultopen="" playbreak="" op="sc='40';on='366';vm='7.9'" TM="1382411417" BKID="202574487" search="类型:联赛;产地:美国;年份:2002;首字母:数字;时长:60分钟-90分钟,90分钟-120分钟,120分钟以上;"
				 TP="g" col="0" pluson="7108" letter="T"  tags="国语DVD版,国语TV版,外语DVD版,外语TV版" isSeries="1" enableSearch2="1" image="2008-05/202574487-321-2008-05-23 16-58-51.jpg" fotm="2" />
<Sub bigtvg="/95_17853_159003.html" 
				id="17853" 
				name="WWE世界摔跤SD" ord="letter" seq="desc" defaultopen="" playbreak="" op="sc='43';on='689';vm='8.5'" TM="1382260729" BKID="202933777" search="产地:美国;首字母:数字;时长:60分钟-90分钟,90分钟-120分钟;"
				 TP="g" col="0" pluson="6819" letter="W"  tags="国语TV版,外语DVD版,外语TV版,外语高清DVD版,外语高清TV版" isSeries="1" enableSearch2="1" image="2011-11/202933777-954-2011-11-07-17-06-44.jpg" fotm="3" />
<Sub bigtvg="/95_17855_159004.html" 
				id="17855" 
				name="WWE世界摔跤SS" ord="letter" seq="desc" defaultopen="" playbreak="" op="sc='40';on='215';vm='7.6'" TM="1382260037" BKID="202934110" search="产地:美国;首字母:数字;时长:30分钟-60分钟;"
				 TP="g" col="0" pluson="7276" letter="W"  tags="DVD版,TV版" isSeries="1" enableSearch2="1" image="2011-11/202934110-954-2011-11-08-11-08-30.jpg" fotm="2" />
<Sub 
				id="47364" 
				name="极限玩家" ord="time" seq="desc" defaultopen="" playbreak="" op="sc='94';on='483';vm='9.1'" TM="1382671221" BKID="203207785" search="首字母:J,Z,数字;时长:30分钟以内;"
				 TP="g" col="0" pluson="6962" letter="J"  tags="国语DVD版,国语TV版,外语TV版" isSeries="1" enableSearch2="1" image="2012-08/203207785-954-2012-08-01-14-59-23.jpg" fotm="2" />
<Sub bigtvg="/95.html" 
				id="22444" 
				name="最新更新" ord="letter" seq="desc" defaultopen="" playbreak="" op="sc='813';on='7339';vm='9.1'" TM="1382697943" BKID="202644643" search="类型:联赛,杯赛,纪录片;产地:中国大陆,美国,英国,法国,西班牙;年份:2010,2009,2004,2002;首字母:G,N,O,R,X,Y,数字;时长:30分钟以内,30分钟-60分钟,60分钟-90分钟,90分钟-120分钟,120分钟以上;"
				 TP="g" col="0" pluson="0" letter="Z"  tags="国语DVD版,国语TV版,国语高清DVD版,国语高清TV版,外语DVD版,外语TV版,外语高清DVD版,外语高清TV版" isSeries="1" enableSearch2="1" image="2009-04/202644643-321-2009-04-24 11-53-39.jpg" fotm="3" />
<Sub bigtvg="/95_23758_159357.html" 
				id="23758" 
				name="西甲联赛" ord="letter" seq="desc" defaultopen="" playbreak="" op="sc='72';on='388';vm='9.1'" TM="1382671221" BKID="202637568" search="类型:联赛;产地:中国大陆,英国,西班牙;年份:2009;首字母:X,Z,数字;时长:30分钟以内,90分钟-120分钟;"
				 TP="g" col="0" pluson="7013" letter="X"  tags="国语DVD版,国语TV版,国语高清DVD版,外语TV版" isSeries="1" enableSearch2="1" image="2009-01/202637568-321-2009-01-12 11-01-06.jpg" fotm="3" />
<Sub bigtvg="/95_22447_166905.html" 
				id="22447" 
				name="天下足球" ord="letter" seq="desc" defaultopen="" playbreak="" op="sc='4';on='224';vm='9.1';nosa='sbG+qQ==';nofaop='sbG+qTvJz7qjO7nj1t0='" TM="1382417178" BKID="400135095" search="产地:中国大陆;年份:2009;首字母:数字;时长:60分钟-90分钟,90分钟-120分钟;"
				 TP="g" col="0" pluson="7150" letter="T"  tags="高清,普通" isSeries="1" enableSearch2="1" image="2011-11/400135095-954-2011-11-22-16-54-42.jpg" fotm="3" dj="1" />
<Sub bigtvg="/95_23847_141511.html" 
				id="23847" 
				name="中国篮球" ord="letter" seq="desc" defaultopen="" playbreak="" op="sc='141';on='678';vm='6.6'" TM="1382582787" BKID="202561629" search="类型:联赛;产地:中国大陆;首字母:C,L,数字;时长:30分钟以内;"
				 TP="g" col="0" pluson="6688" letter="Z"  tags="DVD版,TV版" isSeries="1" enableSearch2="1" image="2007-12/202561629-321-2007-12-05 13-47-14.jpg" fotm="2" />
<Sub bigtvg="/95_22448_155171.html" 
				id="22448" 
				name="极速F1" ord="letter" seq="desc" defaultopen="" playbreak="" op="sc='39';on='223';vm='8.3'" TM="1382697137" BKID="202573433" search="首字母:F,数字;时长:30分钟以内,30分钟-60分钟,60分钟-90分钟,90分钟-120分钟,120分钟以上;"
				 TP="g" col="0" pluson="7137" letter="J"  tags="国语DVD版,国语TV版,外语DVD版,外语TV版" isSeries="1" enableSearch2="1" image="2012-03/202573433-972-2012-03-14-16-42-02.jpg" fotm="2" />
<Sub bigtvg="/95_37366_185781.html" 
				id="37366" 
				name="格斗天下" ord="time" seq="desc" defaultopen="" playbreak="" op="sc='167';on='1329';vm='8'" TM="1382697942" BKID="203230106" search="类型:杯赛;产地:中国大陆;年份:2004;首字母:A,F,G,H,K,L,M,N,P,R,S,T,W,X,Y,Z,数字;时长:30分钟以内,30分钟-60分钟,60分钟-90分钟,90分钟-120分钟,120分钟以上;"
				 TP="g" col="0" pluson="6131" letter="G"  tags="国语DVD版,国语TV版,外语DVD版" isSeries="1" enableSearch2="1" image="2013-06/203230106-954-2013-06-03-14-31-25.jpg" fotm="2" />
<Sub bigtvg="/95_22445_191102.html" 
				id="22445" 
				name="体坛快讯" ord="letter" seq="desc" defaultopen="" playbreak="" op="sc='528';on='2892';vm='8.5'" TM="1382697942" BKID="203203991" search="类型:联赛,杯赛;产地:中国大陆,美国,英国,西班牙;年份:2010,2004;首字母:G,W,Z,数字;时长:30分钟以内;"
				 TP="g" col="0" pluson="4451" letter="T"  tags="国语DVD版,国语TV版,国语流畅TV版,外语TV版" isSeries="1" enableSearch2="1" image="2012-06/203203991-954-2012-06-26-14-22-46.jpg" fotm="2" />
<Sub bigtvg="/95_35568.html" 
				id="35568" 
				name="WWE世界摔跤ME" ord="letter" seq="desc" defaultopen="" playbreak="" op="sc='30';on='477';vm='7.5'" TM="1382671984" BKID="203227101" search="首字母:数字;时长:30分钟-60分钟;"
				 TP="g" col="0" pluson="7004" letter="W"  tags="国语TV版,外语DVD版,外语TV版,外语高清DVD版" enableSearch2="1" image="2013-04/203227101-954-2013-04-16-15-29-59.jpg" />
<Sub bigtvg="/95_41828.html" 
				id="41828" 
				name="美式摔跤合集" ord="time" seq="desc" defaultopen="" playbreak="" op="sc='86';on='261'" TM="1375799453" BKID="400126076" search="类型:联赛;产地:美国;首字母:A,B,C,D,E,F,G,J,K,N,Q,R,S,T,U,W,Y,Z,数字;时长:30分钟以内,30分钟-60分钟,120分钟以上;"
				 TP="g" col="0" pluson="7208" letter="M"  tags="DVD版,TV版,高清DVD版" enableSearch2="1" image="2012-03/400126076-954-2012-03-14-16-45-42.jpg" />
<Sub bigtvg="/95_41475.html" 
				id="41475" 
				name="格斗之夜" ord="online" seq="asc" defaultopen="" playbreak="" op="sc='48';on='8';vm='8'" TM="1381861512" BKID="203232703" search="首字母:A,B,K,L,M,U,W,X,Y,Z,数字;时长:120分钟以上;"
				 TP="g" col="0" pluson="56" letter="G"  enableSearch2="1" image="2013-06/203232703-1072-2013-06-20-11-21-36.jpg" />
<Sub bigtvg="/95_41564.html" 
				id="41564" 
				name="武林风" ord="time" seq="desc" defaultopen="" playbreak="" op="sc='436';on='691';vm='8'" TM="1382518828" BKID="203232703" search="首字母:A,H,Q,T,W,X,Y,Z,数字;时长:120分钟以上;"
				 TP="g" col="0" pluson="0" letter="W"  enableSearch2="1" image="2013-06/203232703-1072-2013-06-20-11-21-36.jpg" />
<Sub bigtvg="/95.html" 
				id="23796" 
				name="中超联赛" ord="letter" seq="desc" defaultopen="" playbreak="" op="sc='180';on='916';vm='7.6'" TM="1382494764" BKID="202624375" search="类型:联赛;产地:中国大陆;年份:2010;首字母:Z,数字;时长:30分钟以内;"
				 TP="g" col="0" pluson="6481" letter="Z"  tags="DVD版,TV版" isSeries="1" enableSearch2="1" image="2013-10/202624375-321-2013-10-12-18-04-30.jpg" fotm="2" />
<Sub bigtvg="/95_23757_141511.html" 
				id="23757" 
				name="英超联赛" ord="letter" seq="desc" defaultopen="" playbreak="" op="sc='85';on='434';vm='8.5'" TM="1382671221" BKID="202637568" search="类型:联赛;产地:英国;首字母:Y,Z,数字;时长:30分钟以内;"
				 TP="g" col="0" pluson="6974" letter="Y"  tags="国语DVD版,国语TV版,外语DVD版,外语TV版" isSeries="1" enableSearch2="1" image="2009-01/202637568-321-2009-01-12 11-01-06.jpg" fotm="2" />
<Sub bigtvg="/95_41990.html" 
				id="41990" 
				name="牛男体育" ord="online" seq="asc" defaultopen="" playbreak="" op="sc='337';vm='8'" TM="1382740226" BKID="203232703" search="首字母:A,B,C,D,E,F,G,H,J,K,L,M,N,P,Q,R,S,T,U,V,W,X,Y,Z,数字;时长:120分钟以上;"
				 TP="g" col="0" pluson="53" letter="N"  enableSearch2="1" image="2013-06/203232703-1072-2013-06-20-11-21-36.jpg" />
<Sub 
				id="48439" 
				name="广州恒大冲击亚冠冠军" ord="online" seq="desc" defaultopen="" playbreak="" op="sc='53';on='404';vm='7.6'" TM="1382697137" BKID="203203313" search="类型:联赛;产地:中国大陆;首字母:H,Y,Z,数字;时长:30分钟以内;"
				 TP="g" col="0" pluson="7117" letter="G"  tags="DVD版,TV版" isSeries="1" enableSearch2="1" image="2012-06/203203313-954-2012-06-16-09-05-48.jpg" fotm="2" />
<Sub 
				id="48319" 
				name="2013中国网球公开赛" ord="online" seq="desc" defaultopen="" playbreak="" op="sc='22';on='97';vm='6.4'" TM="1381222089" BKID="203238658" search="类型:杯赛;产地:中国大陆;首字母:数字;时长:30分钟以内;"
				 TP="g" col="0" pluson="602" letter="数字"  tags="DVD版,TV版" enableSearch2="1" image="2013-08/203238658-954-2013-08-26-11-20-27.jpg" />
<Sub 
				id="48454" 
				name="绿茵骄子C罗VS梅西" ord="online" seq="desc" defaultopen="" playbreak="" op="sc='15';on='79';vm='8.4'" TM="1382665525" BKID="202621971" search="类型:联赛;产地:西班牙;首字母:X,Z,数字;时长:30分钟以内;"
				 TP="g" col="0" pluson="7320" letter="L"  tags="国语DVD版,国语TV版,外语TV版" isSeries="1" enableSearch2="1" image="2008-08/202621971-321-2008-08-29 13-59-01.jpg" fotm="2" />
<Sub bigtvg="/95_41577.html" 
				id="41577" 
				name="篮球教程" ord="online" seq="asc" defaultopen="" playbreak="" op="sc='8';vm='8'" TM="1381110781" BKID="203232703" search="首字母:D,H,K,M,Y,数字;时长:120分钟以上;"
				 TP="g" col="0" pluson="58" letter="L"  enableSearch2="1" image="2013-06/203232703-1072-2013-06-20-11-21-36.jpg" />
<Sub 
				id="48540" 
				name="高端竞技" ord="online" seq="desc" defaultopen="" playbreak="" op="sc='10';on='35';vm='6.4'" TM="1382582787" BKID="203242393" search="首字母:G,L,数字;时长:30分钟以内;"
				 TP="g" col="0" pluson="7382" letter="G"  tags="国语DVD版,国语TV版,外语TV版" isSeries="1" enableSearch2="1" image="2013-10/203242393-873-2013-10-09-19-27-44.jpg" fotm="2" />
<Sub 
				id="48595" 
				name="足球盛宴" ord="online" seq="asc" defaultopen="" playbreak="" op="sc='115';vm='8'" TM="1382757245" BKID="203232703" search="首字母:A,B,C,D,E,F,G,H,J,K,L,M,N,P,Q,R,S,T,W,X,Y,Z,数字;时长:120分钟以上;"
				 TP="g" col="0" pluson="45" letter="Z"  enableSearch2="1" image="2013-06/203232703-1072-2013-06-20-11-21-36.jpg" />
<Sub 
				id="48601" 
				name="拳击赛事经典" ord="online" seq="asc" defaultopen="" playbreak="" op="sc='34';vm='8'" TM="1382667807" BKID="203232703" search="首字母:H,J,M,P,Q,X,Z;时长:120分钟以上;"
				 TP="g" col="0" pluson="48" letter="Q"  enableSearch2="1" image="2013-06/203232703-1072-2013-06-20-11-21-36.jpg" />
<Sub 
				id="48536" 
				name="炫舞人生" ord="online" seq="desc" defaultopen="" playbreak="" op="sc='6';on='23';vm='6'" TM="1382410759" BKID="203242383" search="首字母:Z,数字;时长:30分钟以内;"
				 TP="g" col="0" pluson="7407" letter="Z"  tags="国语DVD版,国语TV版,外语TV版" isSeries="1" enableSearch2="1" image="2013-10/203242383-873-2013-10-09-18-44-22.jpg" fotm="2" />
<Sub bigtvg="/95_33646_183462.html" 
				id="33646" 
				name="爆笑体育" ord="letter" seq="desc" defaultopen="" playbreak="" op="sc='15';on='123';vm='9.1'" TM="1382697943" BKID="203225383" search="类型:联赛;产地:英国;首字母:G,数字;时长:30分钟以内;"
				 TP="g" col="0" pluson="7317" letter="B"  tags="国语,外语" isSeries="1" enableSearch2="1" image="2013-03/203225383-954-2013-03-20-14-42-08.jpg" fotm="2" />
<Sub 
				id="48541" 
				name="中国足球" ord="online" seq="desc" defaultopen="" playbreak="" op="sc='13';on='58';vm='6'" TM="1382583567" BKID="203242397" search="首字母:Z,数字;时长:30分钟以内,30分钟-60分钟;"
				 TP="g" col="0" pluson="7335" letter="Z"  tags="国语" isSeries="1" enableSearch2="1" image="2013-10/203242397-873-2013-10-09-19-40-27.jpg" fotm="2" />
<Sub 
				id="48537" 
				name="健身课堂" ord="online" seq="desc" defaultopen="" playbreak="" op="sc='20';on='81';vm='6'" TM="1382665525" BKID="203242386" search="首字母:T,数字;时长:30分钟以内;"
				 TP="g" col="0" pluson="7341" letter="J"  tags="国语,外语" isSeries="1" enableSearch2="1" image="2013-10/203242386-873-2013-10-09-18-48-37.jpg" fotm="2" />
<Sub 
				id="48731" 
				name="2013索福德全国业余足球联赛" ord="online" seq="desc" defaultopen="" playbreak="" op="sc='8';on='36';vm='6'" TM="1382663965" BKID="203242953" search="首字母:数字;时长:30分钟以内;"
				 TP="g" col="0" pluson="0" letter="数字"  tags="国语" isSeries="1" enableSearch2="1" image="2013-10/203242953-873-2013-10-15-20-16-37.jpg" fotm="2" />
<Sub 
				id="48542" 
				name="篮球世界" ord="online" seq="desc" defaultopen="" playbreak="" op="sc='1';on='7';vm='6'" TM="1382064399" BKID="203242399" search="首字母:数字;时长:30分钟以内;"
				 TP="g" col="0" pluson="7356" letter="L"  tags="国语" isSeries="1" enableSearch2="1" image="2013-10/203242399-873-2013-10-09-19-51-58.jpg" fotm="2" />
</Subs>
